TeamStrange/TeamStrange.py
TeamStrange/__init__.py
TeamStrange-1.2.dist-info/LICENSE
TeamStrange-1.2.dist-info/METADATA
TeamStrange-1.2.dist-info/WHEEL
TeamStrange-1.2.dist-info/top_level.txt
TeamStrange-1.2.dist-info/RECORD
