Metadata-Version: 2.1
Name: TeamStrange
Version: 1.2
Summary: A small package for working with time series. Created by Team Strange.
Home-page: https://git.rwth-aachen.de/swc/teaching/winter-term-21-22/lab-timeseries-synthesizer/team-strange/-/tree/main
Author: Martin Clever
Author-email: martin.clever@rwth-aachen.de
License: UNKNOWN
Platform: UNKNOWN
Classifier: Programming Language :: Python :: 3
Classifier: License :: OSI Approved :: MIT License
Classifier: Operating System :: OS Independent
Requires-Python: >=3.6
License-File: LICENSE
Requires-Dist: pandas
